LICENSE
asyncwica/__init__.py
asyncwica/examples.py
asyncwica/exceptions.py
asyncwica/sseclient.py
asyncwica/stream.py
asyncwica/utils.py
asyncwica-1.3.0.dist-info/LICENSE
asyncwica-1.3.0.dist-info/WHEEL
asyncwica-1.3.0.dist-info/METADATA
asyncwica-1.3.0.dist-info/RECORD
