Metadata-Version: 2.1
Name: asyncwica
Version: 1.3.0
Summary: A simple async python API to access wica-http SSE.
Home-page: https://git.psi.ch/proscan_data/py-wica/-/tree/async
License: GPL v3
Keywords: wica-http,wica,async,SSE,PSI
Author: Niklas Laufkoetter
Author-email: niklas.laufkoetter@psi.ch
Requires-Python: >=3.8,<4.0
Classifier: License :: Other/Proprietary License
Classifier: Programming Language :: Python :: 3
Classifier: Programming Language :: Python :: 3.8
Classifier: Programming Language :: Python :: 3.9
Classifier: Programming Language :: Python :: 3.10
Classifier: Programming Language :: Python :: 3.11
Requires-Dist: httpx (>=0.23.0,<0.24.0)
Project-URL: Repository, https://git.psi.ch/proscan_data/py-wica/-/tree/async
